{"root":[{"assemblyName":"Unity.Collections","nameSpace":"","className":"__JobReflectionRegistrationOutput__1759061347","methodName":"EarlyInit","loadTypes":2,"isUnityClass":true},{"assemblyName":"Unity.Collections","nameSpace":"","className":"$BurstDirectCallInitializer","methodName":"Initialize","loadTypes":2,"isUnityClass":true},{"assemblyName":"Unity.Netcode.Runtime","nameSpace":"Unity.Netcode","className":"NetworkUpdateLoop","methodName":"Initialize","loadTypes":4,"isUnityClass":true},{"assemblyName":"Unity.Netcode.Runtime","nameSpace":"Unity.Netcode","className":"NetworkVariableSerializationTypes","methodName":"InitializeIntegerSerialization","loadTypes":2,"isUnityClass":true},{"assemblyName":"Unity.Netcode.Runtime","nameSpace":"","className":"__JobReflectionRegistrationOutput__2171693258","methodName":"EarlyInit","loadTypes":2,"isUnityClass":true},{"assemblyName":"Unity.Networking.Transport","nameSpace":"","className":"__JobReflectionRegistrationOutput__2846249439","methodName":"EarlyInit","loadTypes":2,"isUnityClass":true},{"assemblyName":"Unity.VisualScripting.Core","nameSpace":"Unity.VisualScripting","className":"RuntimeVSUsageUtility","methodName":"RuntimeInitializeOnLoadBeforeSceneLoad","loadTypes":1,"isUnityClass":true}]}
